hivaapcnt/__init__.py
hivaapcnt/hivaapcnt.py
hivaapcnt/data/__init__.py
hivaapcnt/data/allA.json
hivaapcnt/data/allAll.json
hivaapcnt/data/allB.json
hivaapcnt/data/allC.json
hivaapcnt/data/allCRF01_AE.json
hivaapcnt/data/allCRF02_AG.json
hivaapcnt/data/allD.json
hivaapcnt/data/allF.json
hivaapcnt/data/allG.json
hivaapcnt/data/allOther.json
hivaapcnt/data/artA.json
hivaapcnt/data/artAll.json
hivaapcnt/data/artB.json
hivaapcnt/data/artC.json
hivaapcnt/data/artCRF01_AE.json
hivaapcnt/data/artCRF02_AG.json
hivaapcnt/data/artD.json
hivaapcnt/data/artF.json
hivaapcnt/data/artG.json
hivaapcnt/data/artOther.json
hivaapcnt/data/naiveA.json
hivaapcnt/data/naiveAll.json
hivaapcnt/data/naiveB.json
hivaapcnt/data/naiveC.json
hivaapcnt/data/naiveCRF01_AE.json
hivaapcnt/data/naiveCRF02_AG.json
hivaapcnt/data/naiveD.json
hivaapcnt/data/naiveF.json
hivaapcnt/data/naiveG.json
hivaapcnt/data/naiveOther.json
hivfacts/__init__.py
hivfacts/hivaapcnt.py
hivfacts/hivapobec.py
hivfacts/hivcodonpcnt.py
hivfacts/data/__init__.py
hivfacts/data/aapcnt/rx-all_subtype-A.json
hivfacts/data/aapcnt/rx-all_subtype-B.json
hivfacts/data/aapcnt/rx-all_subtype-C.json
hivfacts/data/aapcnt/rx-all_subtype-CRF01_AE.json
hivfacts/data/aapcnt/rx-all_subtype-CRF02_AG.json
hivfacts/data/aapcnt/rx-all_subtype-D.json
hivfacts/data/aapcnt/rx-all_subtype-F.json
hivfacts/data/aapcnt/rx-all_subtype-G.json
hivfacts/data/aapcnt/rx-all_subtype-all.json
hivfacts/data/aapcnt/rx-all_subtype-other.json
hivfacts/data/aapcnt/rx-art_subtype-A.json
hivfacts/data/aapcnt/rx-art_subtype-B.json
hivfacts/data/aapcnt/rx-art_subtype-C.json
hivfacts/data/aapcnt/rx-art_subtype-CRF01_AE.json
hivfacts/data/aapcnt/rx-art_subtype-CRF02_AG.json
hivfacts/data/aapcnt/rx-art_subtype-D.json
hivfacts/data/aapcnt/rx-art_subtype-F.json
hivfacts/data/aapcnt/rx-art_subtype-G.json
hivfacts/data/aapcnt/rx-art_subtype-all.json
hivfacts/data/aapcnt/rx-art_subtype-other.json
hivfacts/data/aapcnt/rx-naive_subtype-A.json
hivfacts-2019.8.dist-info/METADATA
hivfacts-2019.8.dist-info/WHEEL
hivfacts-2019.8.dist-info/top_level.txt
hivfacts-2019.8.dist-info/zip-safe
hivfacts-2019.8.dist-info/RECORD
